emthub/__init__.py
emthub/api.py
emthub/cim_summary.py
emthub/mpow_utilities.py
emthub/version.py
emthub-0.0.3.dist-info/licenses/LICENSE
emthub-0.0.3.dist-info/METADATA
emthub-0.0.3.dist-info/WHEEL
emthub-0.0.3.dist-info/top_level.txt
emthub-0.0.3.dist-info/RECORD
