Metadata-Version: 2.4
Name: emthub
Version: 0.0.3
Summary: EMTHub: Electromagnetic transient model-building and validation.
Home-page: https://github.com/temcdrm/EMTHub
Author: Tom McDermott
Author-email: tom@meltran.com
License: Apache-2.0
Project-URL: Bug Tracker, https://github.com/temcdrm/EMTHub/issues
Classifier: Operating System :: OS Independent
Classifier: Programming Language :: Python :: 3.8
Classifier: Development Status :: 3 - Alpha
Classifier: Environment :: Console
Classifier: Intended Audience :: Developers
Classifier: Intended Audience :: Education
Classifier: Intended Audience :: Science/Research
Classifier: Topic :: Scientific/Engineering
License-File: LICENSE
Requires-Dist: numpy>=2.1.3
Requires-Dist: pandas>=2.3.3
Requires-Dist: lxml>=5.2.2
Requires-Dist: scipy>=1.14.0
Requires-Dist: networkx>=3.6.1
Requires-Dist: otsrdflib>=0.5.0
Requires-Dist: matplotlib>=3.9.2
Dynamic: license-file
